odoo/addons/sale_stock_cancel_restriction/README.rst
odoo/addons/sale_stock_cancel_restriction/__init__.py
odoo/addons/sale_stock_cancel_restriction/__manifest__.py
odoo/addons/sale_stock_cancel_restriction/i18n/sale_stock_cancel_restriction.pot
odoo/addons/sale_stock_cancel_restriction/models/__init__.py
odoo/addons/sale_stock_cancel_restriction/models/sale_order.py
odoo/addons/sale_stock_cancel_restriction/readme/CONTRIBUTORS.rst
odoo/addons/sale_stock_cancel_restriction/readme/DESCRIPTION.rst
odoo/addons/sale_stock_cancel_restriction/readme/USAGE.rst
odoo/addons/sale_stock_cancel_restriction/static/description/icon.png
odoo/addons/sale_stock_cancel_restriction/static/description/index.html
odoo/addons/sale_stock_cancel_restriction/tests/__init__.py
odoo/addons/sale_stock_cancel_restriction/tests/test_sale_stock_cancel_restriction.py
odoo13_addon_sale_stock_cancel_restriction-13.0.1.0.1.dev5.dist-info/METADATA
odoo13_addon_sale_stock_cancel_restriction-13.0.1.0.1.dev5.dist-info/WHEEL
odoo13_addon_sale_stock_cancel_restriction-13.0.1.0.1.dev5.dist-info/top_level.txt
odoo13_addon_sale_stock_cancel_restriction-13.0.1.0.1.dev5.dist-info/RECORD
